tsvisualize/__init__.py
tsvisualize/visualization.py
tsvisualize-1.0.dist-info/LICENSE
tsvisualize-1.0.dist-info/METADATA
tsvisualize-1.0.dist-info/WHEEL
tsvisualize-1.0.dist-info/top_level.txt
tsvisualize-1.0.dist-info/RECORD
