Metadata-Version: 2.1
Name: tsvisualize
Version: 1.0
Summary: Time-series Visualization with the Matrix Profile and Multidimensional Scaling.
Home-page: https://github.com/ameya98/TimeSeriesVisualization
Author: Ameya Daigavane
Author-email: ameya.d.98@gmail.com
License: MIT
Platform: UNKNOWN
Classifier: Programming Language :: Python :: 2.7
Classifier: Programming Language :: Python :: 3
Classifier: License :: OSI Approved :: MIT License
Classifier: Operating System :: OS Independent
